realtimex_python-1.0.5.dist-info/licenses/LICENSE
src/__init__.py
src/channel.py
src/connection.py
src/realtimex.py
src/types.py
src/utils.py
tests/__init__.py
tests/test_channel.py
tests/test_connection.py
tests/test_realtimex.py
tests/test_utils.py
realtimex_python-1.0.5.dist-info/METADATA
realtimex_python-1.0.5.dist-info/WHEEL
realtimex_python-1.0.5.dist-info/top_level.txt
realtimex_python-1.0.5.dist-info/RECORD
