Metadata-Version: 2.4
Name: realtimex-python
Version: 1.0.5
Summary: Python SDK for RealtimeX real-time messaging service
Home-page: https://gitlab.com/kristinasa/realtimex-py
Author: RealtimeX Team
Author-email: RealtimeX Team <support@realtimex.net>
License: MIT
Project-URL: Homepage, https://gitlab.com/kristinasa/realtimex-py
Project-URL: Repository, https://gitlab.com/kristinasa/realtimex-py
Classifier: Development Status :: 4 - Beta
Classifier: Intended Audience :: Developers
Classifier: License :: OSI Approved :: MIT License
Classifier: Programming Language :: Python :: 3
Classifier: Programming Language :: Python :: 3.7
Classifier: Programming Language :: Python :: 3.8
Classifier: Programming Language :: Python :: 3.9
Classifier: Programming Language :: Python :: 3.10
Classifier: Programming Language :: Python :: 3.11
Requires-Python: >=3.7
License-File: LICENSE
Requires-Dist: python-socketio[client]>=5.10.0
Provides-Extra: dev
Requires-Dist: pytest>=7.0.0; extra == "dev"
Requires-Dist: pytest-cov>=4.0.0; extra == "dev"
Dynamic: author
Dynamic: home-page
Dynamic: license-file
Dynamic: requires-python
